pylogview/__init__.py
pylogview/__main__.py
pylogview/common.py
pylogview/reader.py
pylogview/record.py
pylogview/version.py
pylogview/window.py
pylogview/datefinder/__init__.py
pylogview/datefinder/constants.py
pylogview/datefinder/date_fragment.py
pylogview-0.2.2.dist-info/LICENSE
pylogview-0.2.2.dist-info/METADATA
pylogview-0.2.2.dist-info/WHEEL
pylogview-0.2.2.dist-info/entry_points.txt
pylogview-0.2.2.dist-info/top_level.txt
pylogview-0.2.2.dist-info/RECORD
