Metadata-Version: 2.1
Name: pylogview
Version: 0.2.2
Summary: logview is a simple terminal script that allows you to tail multiple log files in a windowed format.
Home-page: https://github.com/CrazyIvan359/logview
Author: Michael Murton
License: MIT
Keywords: log,logging,tail
Platform: UNKNOWN
Classifier: Development Status :: 4 - Beta
Classifier: License :: OSI Approved :: MIT License
Classifier: Environment :: Console :: Curses
Classifier: Programming Language :: Python
Classifier: Topic :: Home Automation
Classifier: Topic :: Internet :: Log Analysis
Classifier: Topic :: System :: Logging
Classifier: Topic :: Utilities
Requires-Dist: blessings (<2.0,>=1.7)
